patentes_vehiculares_chile/__init__.py
patentes_vehiculares_chile/generador.py
patentes_vehiculares_chile/tipos.py
patentes_vehiculares_chile/validador.py
patentes_vehiculares_chile-0.3.0.dist-info/licenses/LICENSE
patentes_vehiculares_chile-0.3.0.dist-info/METADATA
patentes_vehiculares_chile-0.3.0.dist-info/WHEEL
patentes_vehiculares_chile-0.3.0.dist-info/top_level.txt
patentes_vehiculares_chile-0.3.0.dist-info/RECORD
