Metadata-Version: 2.4
Name: patentes-vehiculares-chile
Version: 0.3.0
Summary: Una librería Python para validar y trabajar con patentes vehiculares chilenas
Author-email: Jorge Gallardo <jorgito899@gmail.com>
License: MIT
Project-URL: Homepage, https://github.com/xatomen/patentes-vehiculares-chile
Project-URL: Repository, https://github.com/xatomen/patentes-vehiculares-chile
Project-URL: Issues, https://github.com/xatomen/patentes-vehiculares-chile/issues
Keywords: patentes,vehiculos,chile,validacion,transporte
Classifier: Development Status :: 4 - Beta
Classifier: Intended Audience :: Developers
Classifier: License :: OSI Approved :: MIT License
Classifier: Operating System :: OS Independent
Classifier: Programming Language :: Python :: 3
Classifier: Programming Language :: Python :: 3.8
Classifier: Programming Language :: Python :: 3.9
Classifier: Programming Language :: Python :: 3.10
Classifier: Programming Language :: Python :: 3.11
Classifier: Programming Language :: Python :: 3.12
Classifier: Topic :: Software Development :: Libraries :: Python Modules
Classifier: Topic :: Utilities
Requires-Python: >=3.8
License-File: LICENSE
Provides-Extra: dev
Requires-Dist: pytest>=7.0; extra == "dev"
Requires-Dist: pytest-cov>=4.0; extra == "dev"
Requires-Dist: black>=22.0; extra == "dev"
Requires-Dist: flake8>=4.0; extra == "dev"
Requires-Dist: mypy>=0.991; extra == "dev"
Requires-Dist: pre-commit>=2.20; extra == "dev"
Dynamic: license-file
